<clinical_study>
  <!-- This xml conforms to an XML Schema at:
    https://clinicaltrials.gov/ct2/html/images/info/public.xsd -->
  <required_header>
    <download_date>ClinicalTrials.gov processed this data on July 28, 2020</download_date>
    <link_text>Link to the current ClinicalTrials.gov record.</link_text>
    <url>https://clinicaltrials.gov/show/NCT03607279</url>
  </required_header>
  <id_info>
    <org_study_id>2016-118</org_study_id>
    <nct_id>NCT03607279</nct_id>
  </id_info>
  <brief_title>Comparison of Plasma Neutrophil Gelatinase - Associated Lipocalin (NGAL) Levels</brief_title>
  <official_title>Comparison of Plasma Neutrophil Gelatinase - Associated Lipocalin (NGAL) Levels After Robot-assisted Laparoscopic Versus Retropubic Radical Prostatectomy</official_title>
  <sponsors>
    <lead_sponsor>
      <agency>Antalya Training and Research Hospital</agency>
      <agency_class>Other</agency_class>
    </lead_sponsor>
  </sponsors>
  <source>Antalya Training and Research Hospital</source>
  <oversight_info>
    <has_dmc>No</has_dmc>
    <is_fda_regulated_drug>No</is_fda_regulated_drug>
    <is_fda_regulated_device>No</is_fda_regulated_device>
  </oversight_info>
  <brief_summary>
    <textblock>
      The purpose of the study is to compare the effect of two surgical techniques (open vs robotic
      assisted) on plasma levels of NGAL (neutrophil gelatinase-associated lipocalin) after radical
      prostatectomy.
    </textblock>
  </brief_summary>
  <detailed_description>
    <textblock>
      Patients undergoing radical prostatectomy are at increased risk of acute kidney injury (AKI)
      because of intraoperative bleeding, obstructive uropathy and older age. In particular
      robot-assisted laparoscopic radical prostatectomy (RALP) which is in increasing demand as an
      alternative surgical option for retropubic radical prostatectomy (RRP) is associated with
      postoperative renal dysfunction because pneumoperitoneum during RALP can decrease cardiac
      output and renal perfusion. NGAL may become important for diagnosis of postoperative AKI
      after urogenital oncosurgery.
    </textblock>
  </detailed_description>
  <overall_status>Completed</overall_status>
  <start_date type="Actual">January 2017</start_date>
  <completion_date type="Actual">August 2017</completion_date>
  <primary_completion_date type="Actual">June 2017</primary_completion_date>
  <study_type>Observational [Patient Registry]</study_type>
  <has_expanded_access>No</has_expanded_access>
  <study_design_info>
    <observational_model>Case-Control</observational_model>
    <time_perspective>Prospective</time_perspective>
  </study_design_info>
  <target_duration>6 Months</target_duration>
  <primary_outcome>
    <measure>Plasma NGAL</measure>
    <time_frame>0 hours, 6 hours and 12 hours after surgery</time_frame>
    <description>Plasma NGAL was determined at baseline, 6 hours and 12 hours after surgery, ng/ml</description>
  </primary_outcome>
  <number_of_groups>2</number_of_groups>
  <enrollment type="Actual">66</enrollment>
  <condition>Prostatectomy</condition>
  <arm_group>
    <arm_group_label>NGAL - retropubic radical prostatectomy</arm_group_label>
    <description>Plasma NGAL was determined at baseline, 6 and 12 hrs after induction of anaesthesia</description>
  </arm_group>
  <arm_group>
    <arm_group_label>NGAL - robotic radical prostatectomy</arm_group_label>
    <description>Plasma NGAL was determined at baseline, 6 and 12 hrs after induction of anaesthesia</description>
  </arm_group>
  <intervention>
    <intervention_type>Procedure</intervention_type>
    <intervention_name>NGAL</intervention_name>
    <arm_group_label>NGAL - retropubic radical prostatectomy</arm_group_label>
    <arm_group_label>NGAL - robotic radical prostatectomy</arm_group_label>
  </intervention>
  <eligibility>
    <study_pop>
      <textblock>
        prostatectomy
      </textblock>
    </study_pop>
    <sampling_method>Probability Sample</sampling_method>
    <criteria>
      <textblock>
        Inclusion Criteria:

          -  patients who undergo prostatectomy

          -  American Society of Anesthesiology (ASA) I-III

        Exclusion Criteria:

          -  preexisting renal disease

          -  emergency surgery

          -  heart failure

          -  peripheral vascular disease
      </textblock>
    </criteria>
    <gender>Male</gender>
    <minimum_age>18 Years</minimum_age>
    <maximum_age>80 Years</maximum_age>
    <healthy_volunteers>No</healthy_volunteers>
  </eligibility>
  <overall_official>
    <last_name>Arzu Karaveli</last_name>
    <role>Principal Investigator</role>
    <affiliation>Netherlands: Ministry of Health, Welfare and Sports</affiliation>
  </overall_official>
  <location>
    <facility>
      <name>Antalya Training and Research Hospital, Department of Anesthesiology and Reanimation</name>
      <address>
        <city>Antalya</city>
        <zip>07100</zip>
        <country>Turkey</country>
      </address>
    </facility>
  </location>
  <location_countries>
    <country>Turkey</country>
  </location_countries>
  <reference>
    <citation>Orsolya M, Attila-Zoltan M, Gherman V, Zaharie F, Bolboaca S, Chira C, Bodolea C, Tomuleasa C, Irimie A, Coman I, Ionescu D. The effect of anaesthetic management on neutrophil gelatinase associated lipocalin (NGAL) levels after robotic surgical oncology. J BUON. 2015 Jan-Feb;20(1):317-24.</citation>
    <PMID>25778333</PMID>
  </reference>
  <reference>
    <citation>Joo EY, Moon YJ, Yoon SH, Chin JH, Hwang JH, Kim YK. Comparison of Acute Kidney Injury After Robot-Assisted Laparoscopic Radical Prostatectomy Versus Retropubic Radical Prostatectomy: A Propensity Score Matching Analysis. Medicine (Baltimore). 2016 Feb;95(5):e2650. doi: 10.1097/MD.0000000000002650.</citation>
    <PMID>26844486</PMID>
  </reference>
  <verification_date>December 2018</verification_date>
  <study_first_submitted>July 23, 2018</study_first_submitted>
  <study_first_submitted_qc>July 30, 2018</study_first_submitted_qc>
  <study_first_posted type="Actual">July 31, 2018</study_first_posted>
  <last_update_submitted>December 18, 2018</last_update_submitted>
  <last_update_submitted_qc>December 18, 2018</last_update_submitted_qc>
  <last_update_posted type="Actual">December 19, 2018</last_update_posted>
  <responsible_party>
    <responsible_party_type>Principal Investigator</responsible_party_type>
    <investigator_affiliation>Antalya Training and Research Hospital</investigator_affiliation>
    <investigator_full_name>Arzu Karaveli</investigator_full_name>
    <investigator_title>Study director</investigator_title>
  </responsible_party>
  <keyword>NGAL</keyword>
  <keyword>Prostatectomy</keyword>
  <keyword>Acute kidney injury</keyword>
  <patient_data>
    <sharing_ipd>No</sharing_ipd>
  </patient_data>
  <!-- Results have not yet been posted for this study                                          -->
</clinical_study>

